.bumpversion.cfg
.coveragerc
.env.example
.flake8
Dockerfile
Makefile
README-dev.md
README.md
VERSION
architecture_overview.md
constraints.txt
pytest
requirements.txt
setup.cfg
setup.py
bridge/__init__.py
bridge/boot.py
bridge/config.py
bridge/confirmation_sender.py
bridge/confirmation_task_planner.py
bridge/constants.py
bridge/contract_abis.py
bridge/contract_validation.py
bridge/event_fetcher.py
bridge/events.py
bridge/main.py
bridge/node_status.py
bridge/service.py
bridge/transfer_recorder.py
bridge/utils.py
bridge/validator_balance_watcher.py
bridge/validator_status_watcher.py
bridge/version.py
bridge/webservice.py
docker/.gitignore
docker/docker-compose-base.yaml
docker/docker-compose-development.yaml
docker/docker-compose-production.yaml
end2end-tests/README.md
end2end-tests/tests/test_transfer.py
tests/conftest.py
tests/keystore.json
tests/password
tests/test_config.py
tests/test_confirmation_sender.py
tests/test_confirmation_task_planner.py
tests/test_contract_validation.py
tests/test_event_fetcher.py
tests/test_main.py
tests/test_service.py
tests/test_transfer_recorder.py
tests/test_utils.py
tests/test_validator_balance_watcher.py
tests/test_validator_status_watcher.py
tests/test_webservice.py
tlbc_bridge.egg-info/PKG-INFO
tlbc_bridge.egg-info/SOURCES.txt
tlbc_bridge.egg-info/dependency_links.txt
tlbc_bridge.egg-info/entry_points.txt
tlbc_bridge.egg-info/requires.txt
tlbc_bridge.egg-info/top_level.txt