Metadata-Version: 1.0
Name: tlbc-bridge
Version: 1.0.0
Summary: token bridge validator client for the Trustlines chain
Home-page: UNKNOWN
Author: UNKNOWN
Author-email: UNKNOWN
License: UNKNOWN
Platform: UNKNOWN
